{"id":110,"name":"Annamae Runolfsdottir","address":{"address":"83901 Allan Skyway","city":"East Efrain","state":"Ohio","zip":"24639"},"reviews":["http://localhost:3000/reviews/440","http://localhost:3000/reviews/441"],"products":["http://localhost:3000/products/859","http://localhost:3000/products/996","http://localhost:3000/products/518","http://localhost:3000/products/810","http://localhost:3000/products/303","http://localhost:3000/products/686","http://localhost:3000/products/119","http://localhost:3000/products/82","http://localhost:3000/products/824","http://localhost:3000/products/402","http://localhost:3000/products/591","http://localhost:3000/products/622","http://localhost:3000/products/859","http://localhost:3000/products/605"]}