{"id":117,"name":"Cordia Cruickshank","address":{"address":"3280 Predovic Parkway","city":"Lake Orval","state":"Wisconsin","zip":"85421-9596"},"reviews":["http://localhost:3000/reviews/468","http://localhost:3000/reviews/469","http://localhost:3000/reviews/470","http://localhost:3000/reviews/471","http://localhost:3000/reviews/472"],"products":["http://localhost:3000/products/448","http://localhost:3000/products/110","http://localhost:3000/products/170","http://localhost:3000/products/240","http://localhost:3000/products/826","http://localhost:3000/products/106","http://localhost:3000/products/843","http://localhost:3000/products/559"]}