{"id":158,"name":"Efrain Morissette","address":{"address":"6145 Conroy Rue","city":"New Charlene","state":"Hawaii","zip":"68613-6231"},"reviews":["http://localhost:3000/reviews/618","http://localhost:3000/reviews/619","http://localhost:3000/reviews/620","http://localhost:3000/reviews/621","http://localhost:3000/reviews/622","http://localhost:3000/reviews/623","http://localhost:3000/reviews/624","http://localhost:3000/reviews/625","http://localhost:3000/reviews/626"],"products":["http://localhost:3000/products/721","http://localhost:3000/products/49","http://localhost:3000/products/824","http://localhost:3000/products/66","http://localhost:3000/products/396","http://localhost:3000/products/947","http://localhost:3000/products/23","http://localhost:3000/products/835","http://localhost:3000/products/282","http://localhost:3000/products/817","http://localhost:3000/products/820","http://localhost:3000/products/0","http://localhost:3000/products/303","http://localhost:3000/products/49","http://localhost:3000/products/274","http://localhost:3000/products/145","http://localhost:3000/products/146","http://localhost:3000/products/929","http://localhost:3000/products/546","http://localhost:3000/products/829"]}