{"id":178,"name":"Providenci Maggio","address":{"address":"213 Chadrick Isle","city":"New Rosemary","state":"Wyoming","zip":"57310-6731"},"reviews":["http://localhost:3000/reviews/702","http://localhost:3000/reviews/703","http://localhost:3000/reviews/704","http://localhost:3000/reviews/705","http://localhost:3000/reviews/706","http://localhost:3000/reviews/707","http://localhost:3000/reviews/708"],"products":["http://localhost:3000/products/856","http://localhost:3000/products/372","http://localhost:3000/products/775","http://localhost:3000/products/917","http://localhost:3000/products/203","http://localhost:3000/products/883","http://localhost:3000/products/91","http://localhost:3000/products/810","http://localhost:3000/products/380","http://localhost:3000/products/947","http://localhost:3000/products/829","http://localhost:3000/products/700","http://localhost:3000/products/5","http://localhost:3000/products/428","http://localhost:3000/products/887","http://localhost:3000/products/564","http://localhost:3000/products/413","http://localhost:3000/products/918","http://localhost:3000/products/346"]}