{"id":182,"name":"Jordane Funk","address":{"address":"20061 Lehner Ford","city":"New Jamal","state":"Montana","zip":"43004"},"reviews":["http://localhost:3000/reviews/724"],"products":["http://localhost:3000/products/642","http://localhost:3000/products/428","http://localhost:3000/products/946","http://localhost:3000/products/677","http://localhost:3000/products/320","http://localhost:3000/products/858","http://localhost:3000/products/116","http://localhost:3000/products/462","http://localhost:3000/products/602","http://localhost:3000/products/444","http://localhost:3000/products/121","http://localhost:3000/products/498","http://localhost:3000/products/586","http://localhost:3000/products/416","http://localhost:3000/products/935","http://localhost:3000/products/479"]}