{"id":3,"name":"Karianne Beatty","address":{"address":"060 Metz Mission","city":"New Miguelstad","state":"Tennessee","zip":"49802-9703"},"reviews":["http://localhost:3000/reviews/5","http://localhost:3000/reviews/6","http://localhost:3000/reviews/7","http://localhost:3000/reviews/8","http://localhost:3000/reviews/9","http://localhost:3000/reviews/10"],"products":["http://localhost:3000/products/909","http://localhost:3000/products/453","http://localhost:3000/products/403","http://localhost:3000/products/996","http://localhost:3000/products/388","http://localhost:3000/products/469","http://localhost:3000/products/74","http://localhost:3000/products/187","http://localhost:3000/products/596","http://localhost:3000/products/553","http://localhost:3000/products/41","http://localhost:3000/products/733"]}