{"id":87,"name":"Nettie Paucek","address":{"address":"92955 Heller Mountain","city":"Kuhicfort","state":"Wisconsin","zip":"95410"},"reviews":["http://localhost:3000/reviews/351","http://localhost:3000/reviews/352","http://localhost:3000/reviews/353","http://localhost:3000/reviews/354"],"products":["http://localhost:3000/products/730","http://localhost:3000/products/213","http://localhost:3000/products/656","http://localhost:3000/products/477","http://localhost:3000/products/385","http://localhost:3000/products/700","http://localhost:3000/products/136","http://localhost:3000/products/330","http://localhost:3000/products/441","http://localhost:3000/products/507","http://localhost:3000/products/583","http://localhost:3000/products/993","http://localhost:3000/products/950","http://localhost:3000/products/197","http://localhost:3000/products/286"]}