{"id":985,"reviewer":"http://localhost:3000/users/248","product":"http://localhost:3000/products/791","rating":5,"summary":"Nam ea nam aperiam facere voluptate voluptatem reprehenderit dolore.","review":"Vero at sint rerum placeat omnis mollitia. Commodi sunt quibusdam officia et molestias delectus alias eius tenetur. Rerum atque quia enim qui illum nemo odit. Excepturi fugiat consectetur suscipit enim ducimus error. Earum ratione laudantium iusto quia ut occaecati error deleniti sit. Nihil quidem ea et reiciendis."}