{"id":482,"reviewer":"http://localhost:3000/users/130","product":"http://localhost:3000/products/728","rating":1,"summary":"Iusto eius dolorem ducimus alias et molestiae quo.","review":"Nemo et nobis. Qui possimus voluptates iure consectetur quo sed et distinctio. Perferendis hic temporibus amet et sequi. Nulla sit quis. Suscipit aut qui sint suscipit exercitationem facere velit dolorem soluta. In voluptas voluptate fugiat at accusamus dolores minus et.","url":"http://localhost:3000/reviews/482"}