{"id":512,"reviewer":"http://localhost:3000/users/141","product":"http://localhost:3000/products/218","rating":4,"summary":"Quasi quis occaecati dolor molestiae amet reprehenderit vero quam.","review":"Veritatis quibusdam aut aut blanditiis amet velit iure. Quis quisquam quasi. Praesentium velit voluptatem. Non aliquid officiis quasi natus natus maiores alias. Quas iure rerum. Totam tempore repellendus aut sit ullam aperiam distinctio reiciendis voluptatibus.","url":"http://localhost:3000/reviews/512"}