{"id":706,"reviewer":"http://localhost:3000/users/196","product":"http://localhost:3000/products/840","rating":5,"summary":"Dolores quaerat quasi id nam voluptas eligendi deserunt.","review":"Dicta cumque et laborum. Est suscipit molestiae velit aperiam et. Ut odit impedit neque consequuntur dignissimos amet sapiente. Et quaerat cumque ducimus pariatur aliquam eius quis eos. Dolorem itaque enim temporibus sequi consequatur occaecati voluptatem modi minima.","url":"http://localhost:3000/reviews/706"}