{"id":178,"name":"Demario Donnelly","address":{"address":"131 Schaden Turnpike","city":"Lake Aileenport","state":"Nebraska","zip":"11148-5334"},"reviews":["http://localhost:3000/reviews/648","http://localhost:3000/reviews/649","http://localhost:3000/reviews/650","http://localhost:3000/reviews/651","http://localhost:3000/reviews/652","http://localhost:3000/reviews/653"],"products":["http://localhost:3000/products/341","http://localhost:3000/products/425","http://localhost:3000/products/950","http://localhost:3000/products/45","http://localhost:3000/products/282","http://localhost:3000/products/487","http://localhost:3000/products/146","http://localhost:3000/products/928","http://localhost:3000/products/733","http://localhost:3000/products/181","http://localhost:3000/products/849","http://localhost:3000/products/175","http://localhost:3000/products/619","http://localhost:3000/products/541","http://localhost:3000/products/592","http://localhost:3000/products/743","http://localhost:3000/products/567","http://localhost:3000/products/96","http://localhost:3000/products/600"],"url":"http://localhost:3000/users/178"}