{"id":29,"name":"Jeanne Feil","address":{"address":"08053 Bins Canyon","city":"Port Demetrisland","state":"Iowa","zip":"45705-7720"},"reviews":["http://localhost:3000/reviews/99","http://localhost:3000/reviews/100","http://localhost:3000/reviews/101","http://localhost:3000/reviews/102"],"products":["http://localhost:3000/products/694","http://localhost:3000/products/556","http://localhost:3000/products/128","http://localhost:3000/products/556","http://localhost:3000/products/277","http://localhost:3000/products/451","http://localhost:3000/products/446","http://localhost:3000/products/275","http://localhost:3000/products/646","http://localhost:3000/products/589","http://localhost:3000/products/78","http://localhost:3000/products/685","http://localhost:3000/products/746","http://localhost:3000/products/422","http://localhost:3000/products/354","http://localhost:3000/products/777","http://localhost:3000/products/391","http://localhost:3000/products/201","http://localhost:3000/products/98","http://localhost:3000/products/920","http://localhost:3000/products/187","http://localhost:3000/products/878","http://localhost:3000/products/506","http://localhost:3000/products/358"],"url":"http://localhost:3000/users/29"}